{
  "players": [
    "Elena",
    "Mitko"
  ],
  "total-score": {
    "Elena": 310,
    "Mitko": 335
  },
  "scores": [
    {
      "chance": 10,
      "minus": 18,
      "plus": 23,
      "rigole": 50,
      "yams": 50,
      "carre": 40,
      "grande-suite": 0,
      "petite-suite": 25,
      "brelan": 25,
      "full": 30,
      "6": 0,
      "5": 10,
      "4": 12,
      "3": 9,
      "2": 6,
      "1": 2
    },
    {
      "chance": 18,
      "minus": 21,
      "plus": 27,
      "rigole": 50,
      "yams": 0,
      "carre": 40,
      "grande-suite": 35,
      "petite-suite": 25,
      "brelan": 27,
      "full": 30,
      "6": 18,
      "5": 15,
      "4": 12,
      "3": 9,
      "2": 6,
      "1": 2
    }
  ]
}