{
  "players": [
    "Elena",
    "Mitko"
  ],
  "total-score": {
    "Elena": 269,
    "Mitko": 287
  },
  "scores": [
    {
      "chance": 23,
      "minus": 20,
      "plus": 24,
      "rigole": 0,
      "yams": 0,
      "carre": 40,
      "grande-suite": 0,
      "petite-suite": 25,
      "brelan": 14,
      "full": 30,
      "6": 18,
      "5": 15,
      "4": 12,
      "3": 9,
      "2": 6,
      "1": 3
    },
    {
      "chance": 22,
      "minus": 12,
      "plus": 25,
      "rigole": 50,
      "yams": 0,
      "carre": 40,
      "grande-suite": 0,
      "petite-suite": 25,
      "brelan": 23,
      "full": 30,
      "6": 18,
      "5": 15,
      "4": 12,
      "3": 6,
      "2": 6,
      "1": 3
    }
  ]
}